scrapy_rss_exporter/exporters.py
scrapy_rss_exporter/items.py
scrapy_rss_exporter-0.2.dist-info/LICENSE
scrapy_rss_exporter-0.2.dist-info/METADATA
scrapy_rss_exporter-0.2.dist-info/WHEEL
scrapy_rss_exporter-0.2.dist-info/top_level.txt
scrapy_rss_exporter-0.2.dist-info/RECORD
