Metadata-Version: 2.1
Name: scrapy-rss-exporter
Version: 0.2
Summary: An RSS Exporter for Scrapy
Home-page: https://github.com/ljanyst/scrapy-rss-exporter
Author: Lukasz Janyst
Author-email: xyz@jany.st
License: BSD License
Platform: UNKNOWN
Classifier: Framework :: Scrapy
Classifier: Development Status :: 4 - Beta
Classifier: Intended Audience :: Developers
Classifier: License :: OSI Approved :: BSD License
Classifier: Operating System :: OS Independent
Classifier: Programming Language :: Python
Classifier: Programming Language :: Python :: 3
Classifier: Programming Language :: Python :: 3.5
Classifier: Programming Language :: Python :: 3.6
Classifier: Topic :: Internet :: WWW/HTTP
Classifier: Topic :: Software Development :: Libraries :: Python Modules
Requires-Dist: scrapy (>=1.4.0)
